freerec/__init__.py
freerec/__main__.py
freerec/criterions.py
freerec/ddp.py
freerec/dict2obj.py
freerec/graph.py
freerec/launcher.py
freerec/metrics.py
freerec/parser.py
freerec/utils.py
freerec/data/__init__.py
freerec/data/fields.py
freerec/data/normalizer.py
freerec/data/tags.py
freerec/data/utils.py
freerec/data/datasets/__init__.py
freerec/data/datasets/allrecipes.py
freerec/data/datasets/amazon2014.py
freerec/data/datasets/amazon2018.py
freerec/data/datasets/amazon2023.py
freerec/data/datasets/base.py
freerec/data/datasets/criteo.py
freerec/data/datasets/frappe.py
freerec/data/datasets/gowalla.py
freerec/data/datasets/microlens.py
freerec/data/datasets/movielens.py
freerec/data/datasets/steam.py
freerec/data/datasets/tiktok.py
freerec/data/datasets/yelp.py
freerec/data/postprocessing/__init__.py
freerec/data/postprocessing/base.py
freerec/data/postprocessing/base.pyi
freerec/data/postprocessing/column.py
freerec/data/postprocessing/other.py
freerec/data/postprocessing/row.py
freerec/data/postprocessing/sampler.py
freerec/data/postprocessing/source.py
freerec/data/preprocessing/__init__.py
freerec/data/preprocessing/amazon2023.py
freerec/data/preprocessing/base.py
freerec/models/__init__.py
freerec/models/base.py
freerec/models/nn.py
freerec/models/nn/__init__.py
freerec/models/nn/attn.py
freerec/models/nn/ffn.py
freerec/models/nn/utils.py
freerec-0.9.5.dist-info/LICENSE
freerec-0.9.5.dist-info/METADATA
freerec-0.9.5.dist-info/WHEEL
freerec-0.9.5.dist-info/entry_points.txt
freerec-0.9.5.dist-info/top_level.txt
freerec-0.9.5.dist-info/RECORD
