Metadata-Version: 2.2
Name: freerec
Version: 0.9.5
Summary: PyTorch library for recommender systems
Home-page: https://github.com/MTandHJ/freerec
Author: MTandHJ
Author-email: congxueric@gmail.com
License: MIT License
Classifier: Programming Language :: Python :: 3
Classifier: License :: OSI Approved :: MIT License
Classifier: Operating System :: OS Independent
Requires-Python: >=3.9
License-File: LICENSE
Requires-Dist: polars>=1.9.0
Requires-Dist: PyYAML>=6.0
Requires-Dist: tensorboard>=2.10.0
Requires-Dist: prettytable>=3.4.1
Dynamic: author
Dynamic: author-email
Dynamic: classifier
Dynamic: description
Dynamic: description-content-type
Dynamic: home-page
Dynamic: license
Dynamic: requires-dist
Dynamic: requires-python
Dynamic: summary
